pystereoalgeval/__init__.py
pystereoalgeval/evaluation_app.py
pystereoalgeval-0.2.3.dist-info/LICENSE
pystereoalgeval-0.2.3.dist-info/METADATA
pystereoalgeval-0.2.3.dist-info/WHEEL
pystereoalgeval-0.2.3.dist-info/top_level.txt
pystereoalgeval-0.2.3.dist-info/RECORD
