Metadata-Version: 2.1
Name: pystereoalgeval
Version: 0.2.3
Summary: Automated Stereo Algorithm Evaluation
Home-page: https://github.com/dettoman/py_stereo_alg_eval
Author: Benedikt Bieberle
Author-email: benedikt.bieberle@tu-ilmenau.de
License: UNKNOWN
Platform: UNKNOWN
Classifier: Programming Language :: Python :: 3
Classifier: Development Status :: 3 - Alpha
Classifier: Environment :: Console
Classifier: License :: OSI Approved :: GNU Affero General Public License v3 or later (AGPLv3+)
Classifier: Operating System :: OS Independent
Classifier: Natural Language :: English
Classifier: Natural Language :: German
Classifier: Topic :: Software Development :: Testing
